{
  "ngDeps": {
    "1": "components",
    "3": [
      {
        "1": "package:angular2/core.dart",
        "5": false
      },
      {
        "1": "package:angular2/router.dart",
        "5": false
      }
    ],
    "5": [
      {
        "1": "AppComponent",
        "4": [
          {
            "1": "RouteConfig",
            "2": [
              "const [const Route(component: CardsComponent, path: '/', name: 'Cards', useAsDefault: true), const Route(component: ArticleComponent, path: '/articles/:id', name: 'Articles')]"
            ],
            "4": false
          }
        ],
        "5": [
          {
            "1": "Router",
            "4": "router"
          }
        ],
        "6": [
          "OnInit"
        ],
        "7": [
          {
            "2": "COMPONENT_DIRECTIVES"
          },
          {
            "2": "ROUTER_DIRECTIVES"
          }
        ]
      },
      {
        "1": "NavbarComponent"
      },
      {
        "1": "CardsComponent",
        "7": [
          {
            "2": "COMPONENT_DIRECTIVES"
          },
          {
            "2": "ROUTER_DIRECTIVES"
          }
        ]
      },
      {
        "1": "CardComponent",
        "5": [
          {
            "1": "Router",
            "4": "router"
          }
        ],
        "6": [
          "OnInit"
        ],
        "7": [
          {
            "2": "COMPONENT_DIRECTIVES"
          },
          {
            "2": "ROUTER_DIRECTIVES"
          }
        ]
      },
      {
        "1": "ArticleComponent",
        "7": [
          {
            "2": "COMPONENT_DIRECTIVES"
          }
        ]
      }
    ],
    "6": "components.dart"
  },
  "type": {
    "STYLES": {
      "class": "Identifier",
      "name": "STYLES",
      "moduleUrl": "asset:saga/lib/components.dart",
      "prefix": null,
      "value": null
    },
    "COMPONENT_DIRECTIVES": {
      "class": "Identifier",
      "name": "COMPONENT_DIRECTIVES",
      "moduleUrl": "asset:saga/lib/components.dart",
      "prefix": null,
      "value": [
        {
          "class": "Identifier",
          "name": "AppComponent",
          "moduleUrl": null,
          "prefix": null,
          "value": null
        },
        {
          "class": "Identifier",
          "name": "NavbarComponent",
          "moduleUrl": null,
          "prefix": null,
          "value": null
        },
        {
          "class": "Identifier",
          "name": "CardComponent",
          "moduleUrl": null,
          "prefix": null,
          "value": null
        },
        {
          "class": "Identifier",
          "name": "CardsComponent",
          "moduleUrl": null,
          "prefix": null,
          "value": null
        },
        {
          "class": "Identifier",
          "name": "ArticleComponent",
          "moduleUrl": null,
          "prefix": null,
          "value": null
        }
      ]
    },
    "AppComponent": {
      "class": "Directive",
      "isComponent": true,
      "selector": "app",
      "exportAs": null,
      "type": {
        "class": "Type",
        "name": "AppComponent",
        "moduleUrl": "asset:saga/lib/components.dart",
        "prefix": null,
        "isHost": false,
        "value": null,
        "diDeps": [
          {
            "token": {
              "value": null,
              "identifier": {
                "class": "Identifier",
                "name": "Router",
                "moduleUrl": null,
                "prefix": null,
                "value": null
              },
              "identifierIsInstance": false
            },
            "query": null,
            "viewQuery": null,
            "value": null,
            "isAttribute": false,
            "isSelf": false,
            "isHost": false,
            "isSkipSelf": false,
            "isOptional": false,
            "isValue": false
          }
        ]
      },
      "changeDetection": 5,
      "inputs": {},
      "outputs": {},
      "hostListeners": {},
      "hostProperties": {},
      "hostAttributes": {},
      "lifecycleHooks": [
        0
      ],
      "template": {
        "encapsulation": 0,
        "template": "<navbar>\n</navbar>\n\n<router-outlet></router-outlet>\n",
        "templateUrl": "asset:saga/lib/app_component.html",
        "styles": [],
        "styleUrls": [
          "asset:saga/lib/component.css"
        ],
        "ngContentSelectors": []
      },
      "providers": [
        {
          "class": "Identifier",
          "name": "ROUTER_PROVIDERS",
          "moduleUrl": null,
          "prefix": null,
          "value": null
        }
      ],
      "viewProviders": [],
      "queries": [],
      "viewQueries": []
    },
    "NavbarComponent": {
      "class": "Directive",
      "isComponent": true,
      "selector": "navbar",
      "exportAs": null,
      "type": {
        "class": "Type",
        "name": "NavbarComponent",
        "moduleUrl": "asset:saga/lib/components.dart",
        "prefix": null,
        "isHost": false,
        "value": null,
        "diDeps": []
      },
      "changeDetection": 5,
      "inputs": {},
      "outputs": {},
      "hostListeners": {},
      "hostProperties": {},
      "hostAttributes": {},
      "lifecycleHooks": [],
      "template": {
        "encapsulation": 0,
        "template": "<nav>\n  <div class=\"nav-wrapper blue-grey darken-2\">\n    <form>\n      <div class=\"input-field\">\n        <input id=\"search\" type=\"search\" required>\n        <label for=\"search\"><i class=\"material-icons\">search</i></label>\n        <i class=\"material-icons\">close</i>\n      </div>\n    </form>\n  </div>\n</nav>\n",
        "templateUrl": "asset:saga/lib/navbar_component.html",
        "styles": [],
        "styleUrls": [
          "asset:saga/lib/component.css"
        ],
        "ngContentSelectors": []
      },
      "providers": [],
      "viewProviders": [],
      "queries": [],
      "viewQueries": []
    },
    "CardsComponent": {
      "class": "Directive",
      "isComponent": true,
      "selector": "cards",
      "exportAs": null,
      "type": {
        "class": "Type",
        "name": "CardsComponent",
        "moduleUrl": "asset:saga/lib/components.dart",
        "prefix": null,
        "isHost": false,
        "value": null,
        "diDeps": []
      },
      "changeDetection": 5,
      "inputs": {},
      "outputs": {},
      "hostListeners": {},
      "hostProperties": {},
      "hostAttributes": {},
      "lifecycleHooks": [],
      "template": {
        "encapsulation": 2,
        "template": "<div class=\"container\">\n  <div class=\"row\">\n    <card></card>\n    <card></card>\n    <card></card>\n    <card></card>\n    <card></card>\n  </div>\n</div>\n",
        "templateUrl": "asset:saga/lib/cards_component.html",
        "styles": [],
        "styleUrls": [],
        "ngContentSelectors": []
      },
      "providers": [],
      "viewProviders": [],
      "queries": [],
      "viewQueries": []
    },
    "CardComponent": {
      "class": "Directive",
      "isComponent": true,
      "selector": "card",
      "exportAs": null,
      "type": {
        "class": "Type",
        "name": "CardComponent",
        "moduleUrl": "asset:saga/lib/components.dart",
        "prefix": null,
        "isHost": false,
        "value": null,
        "diDeps": [
          {
            "token": {
              "value": null,
              "identifier": {
                "class": "Identifier",
                "name": "Router",
                "moduleUrl": null,
                "prefix": null,
                "value": null
              },
              "identifierIsInstance": false
            },
            "query": null,
            "viewQuery": null,
            "value": null,
            "isAttribute": false,
            "isSelf": false,
            "isHost": false,
            "isSkipSelf": false,
            "isOptional": false,
            "isValue": false
          }
        ]
      },
      "changeDetection": 5,
      "inputs": {},
      "outputs": {},
      "hostListeners": {},
      "hostProperties": {},
      "hostAttributes": {},
      "lifecycleHooks": [
        0
      ],
      "template": {
        "encapsulation": 0,
        "template": "<div class=\"col s12\">\n  <div class=\"card hoverable\">\n    <div class=\"card-clickable\" [routerLink]=\"['/Articles', id]\">\n      <div class=\"card-image\">\n      <img src=\"img/1.jpg\">\n      <span class=\"card-title truncate\">History Article</span>\n    </div>\n    <div class=\"card-content\">\n      <div class=\"card-header truncate\">\n        <div class=\"chip\">\n          <img src=\"img/1.jpg\" alt=\"Contact Person\">\n          <span>Jane Doe</span>\n        </div>\n        <label>2016.09.01</label>\n      </div>\n      <div class=\"divider\"></div>\n        <p class=\"flow-text\">I am a very simple card. I am good at containing small bits of information.\n       I am convenient because I require little markup to use effectively.</p>\n    </div>\n  </div>\n    <div class=\"card-action\">\n      <a href=\"\" class=\"red-text\"><i class=\"material-icons\">favorite_border</i></a>\n      <a href=\"\" class=\"blue-text\"><i class=\"material-icons\">share</i></a>\n      <a href=\"\" class=\"grey-text text-darken-2\"><i class=\"material-icons\">playlist_add</i></a>\n      <a href=\"\" class=\"green-text\"><i class=\"material-icons\">done</i></a>\n\n    </div>\n  </div>\n</div>\n",
        "templateUrl": "asset:saga/lib/card_component.html",
        "styles": [],
        "styleUrls": [
          "asset:saga/lib/component.css"
        ],
        "ngContentSelectors": []
      },
      "providers": [],
      "viewProviders": [],
      "queries": [],
      "viewQueries": []
    },
    "ArticleComponent": {
      "class": "Directive",
      "isComponent": true,
      "selector": "article",
      "exportAs": null,
      "type": {
        "class": "Type",
        "name": "ArticleComponent",
        "moduleUrl": "asset:saga/lib/components.dart",
        "prefix": null,
        "isHost": false,
        "value": null,
        "diDeps": []
      },
      "changeDetection": 5,
      "inputs": {},
      "outputs": {},
      "hostListeners": {},
      "hostProperties": {},
      "hostAttributes": {},
      "lifecycleHooks": [],
      "template": {
        "encapsulation": 0,
        "template": "<div class=\"fixed-action-btn horizontal\" style=\"bottom: 45px; right: 24px;\">\n  <a class=\"btn-floating btn-large blue-grey darken-2\">\n    <i class=\"large material-icons\">share</i>\n  </a>\n  <ul>\n    <li><a class=\"btn-floating blue-grey lighten-3\"><i class=\"material-icons\">email</i></a></li>\n    <li><a class=\"btn-floating blue-grey lighten-2\"><i class=\"material-icons\">content_copy</i></a></li>\n    <li><a class=\"btn-floating blue-grey lighten-1\"><i class=\"material-icons\">chat_bubble</i></a></li>\n  </ul>\n</div>\n\n<div class=\"article\">\n    <!-- Article content here -->\n    <div class=\"article-header\">\n      <img class=\"responsive-img\" src=\"img/1.jpg\">\n      <div class=\"overlay\"></div>\n      <div class=\"container\">\n        <span class=\"article-title\">Article Title</span>\n      </div>\n    </div>\n    <div class=\"container\">\n      <div class=\"row\">\n        <div class=\"col s12\">\n          <div class=\"article-bar truncate\">\n            <div class=\"chip article-author\">\n              <img src=\"img/1.jpg\" alt=\"Contact Person\">\n              <span>Jane Doe</span>\n            </div>\n            <label>2015.09.01</label>\n          </div>\n\n\n          <div class=\"divider\"></div>\n\n\n          <!-- Article contents -->\n          <div class=\"section flow-text\">\n            <p class=\"title\">An Introduction</p>\n            <p>Lorem ipsum dolor sit amet<sup>[1]</sup>, consectetur adipiscing elit. Quisque eu sodales justo. Donec in imperdiet odio. Aenean dignissim, ex fringilla congue feugiat, odio arcu volutpat orci, ut viverra augue lorem blandit augue. Pellentesque porta sem lacus. Ut mauris enim, lobortis vel quam bibendum, gravida dignissim mi. Morbi cursus molestie turpis ut porta. Curabitur quis ultrices metus. Pellentesque sollicitudin a risus eu venenatis. Quisque blandit, purus at viverra scelerisque, neque lacus varius leo, vel fermentum purus dui id tellus. Pellentesque vel aliquam massa, sit amet blandit augue. Pellentesque eu finibus risus, vel accumsan orci.</p>\n            <blockquote><small>\n              Lorem ipsum dolor sit amet, consectetur adipiscing elit. Quisque eu sodales justo. Donec in imperdiet odio. Aenean dignissim, ex fringilla congue feugiat, odio arcu volutpat orci, ut viverra augue\n            </small></blockquote>\n            <p>Lorem ipsum dolor sit amet, consectetur adipiscing elit. Quisque eu sodales justo. Donec in imperdiet odio. Aenean dignissim, ex fringilla congue feugiat, odio arcu volutpat orci, ut viverra augue lorem blandit augue. Pellentesque porta sem lacus. Ut mauris enim, lobortis vel quam bibendum, gravida dignissim mi. Morbi cursus molestie turpis ut porta. Curabitur quis ultrices metus. Pellentesque sollicitudin a risus eu venenatis. Quisque blandit, purus at viverra scelerisque, neque lacus varius leo, vel fermentum purus dui id tellus. Pellentesque vel aliquam massa, sit amet blandit augue. Pellentesque eu finibus risus, vel accumsan orci.</p>\n            <p>Lorem ipsum dolor sit amet, consectetur adipiscing elit. Quisque eu sodales justo. Donec in imperdiet odio. Aenean dignissim, ex fringilla congue feugiat, odio arcu volutpat orci, ut viverra augue lorem blandit augue. Pellentesque porta sem lacus. Ut mauris enim, lobortis vel quam bibendum, gravida dignissim mi. Morbi cursus molestie turpis ut porta. Curabitur quis ultrices metus. Pellentesque sollicitudin a risus eu venenatis. Quisque blandit, purus at viverra scelerisque, neque lacus varius leo, vel fermentum purus dui id tellus. Pellentesque vel aliquam massa, sit amet blandit augue. Pellentesque eu finibus risus, vel accumsan orci.</p>\n            <p>Lorem ipsum dolor sit amet, consectetur adipiscing elit. Quisque eu sodales justo. Donec in imperdiet odio. Aenean dignissim, ex fringilla congue feugiat, odio arcu volutpat orci, ut viverra augue lorem blandit augue. Pellentesque porta sem lacus. Ut mauris enim, lobortis vel quam bibendum, gravida dignissim mi. Morbi cursus molestie turpis ut porta. Curabitur quis ultrices metus. Pellentesque sollicitudin a risus eu venenatis. Quisque blandit, purus at viverra scelerisque, neque lacus varius leo, vel fermentum purus dui id tellus. Pellentesque vel aliquam massa, sit amet blandit augue. Pellentesque eu finibus risus, vel accumsan orci.</p>\n            <p>Lorem ipsum dolor sit amet, consectetur adipiscing elit. Quisque eu sodales justo. Donec in imperdiet odio. Aenean dignissim, ex fringilla congue feugiat, odio arcu volutpat orci, ut viverra augue lorem blandit augue. Pellentesque porta sem lacus. Ut mauris enim, lobortis vel quam bibendum, gravida dignissim mi. Morbi cursus molestie turpis ut porta. Curabitur quis ultrices metus. Pellentesque sollicitudin a risus eu venenatis. Quisque blandit, purus at viverra scelerisque, neque lacus varius leo, vel fermentum purus dui id tellus. Pellentesque vel aliquam massa, sit amet blandit augue. Pellentesque eu finibus risus, vel accumsan orci.</p>\n          </div>\n\n          <div class=\"divider\"></div>\n          <ol>\n            <li><p class=\"flow-text\"><small><i>Note.</i> From “Title of the article,” by W. Jones and R. Smith, 2007, <i>Journal Title</i>, 21, p. 122. Copyright 2007 by Copyright Holder. Reprinted with permission.</small></p></li>\n          </ol>\n\n      </div>\n    </div>\n  </div>\n</div>\n",
        "templateUrl": "asset:saga/lib/article_component.html",
        "styles": [],
        "styleUrls": [
          "asset:saga/lib/component.css"
        ],
        "ngContentSelectors": []
      },
      "providers": [],
      "viewProviders": [],
      "queries": [],
      "viewQueries": []
    }
  },
  "alias": {
    "COMPONENT_DIRECTIVES": [
      "AppComponent",
      "NavbarComponent",
      "CardComponent",
      "CardsComponent",
      "ArticleComponent"
    ]
  }
}